test/__init__.py
test/test_iddata.py
test/test_reference.py
test/test_utils.py
test/test_vrft.py
vrft/__init__.py
vrft/extended_tf.py
vrft/iddata.py
vrft/utils.py
vrft/vrft_algo.py
pythonvrft-0.0.5.dist-info/LICENSE
pythonvrft-0.0.5.dist-info/METADATA
pythonvrft-0.0.5.dist-info/WHEEL
pythonvrft-0.0.5.dist-info/top_level.txt
pythonvrft-0.0.5.dist-info/RECORD
