Metadata-Version: 2.1
Name: pythonvrft
Version: 0.0.5
Summary: VRFT Python Library
Home-page: https://github.com/rssalessio/PythonVRFT/
Author: Alessio Russo
Author-email: alessior@kth.se
License: GPL3
Keywords: VRFT,Virtual Reference Feedback Tuning,Data Driven Control,Adaptive Control
Platform: UNKNOWN
Classifier: Programming Language :: Python :: 3
Classifier: License :: OSI Approved :: GNU General Public License v3 (GPLv3)
Classifier: Operating System :: OS Independent
Classifier: Development Status :: 3 - Alpha
Classifier: Topic :: Scientific/Engineering
Requires-Python: >=3.5
Requires-Dist: scipy
Requires-Dist: numpy
